{
  "kind": "singleType",
  "collectionName": "not_founds",
  "info": {
    "singularName": "not-found",
    "pluralName": "not-founds",
    "displayName": "Not Found",
    "description": ""
  },
  "options": {
    "draftAndPublish": true
  },
  "pluginOptions": {
    "i18n": {
      "localized": true
    }
  },
  "attributes": {
    "title": {
      "type": "string",
      "pluginOptions": {
        "i18n": {
          "localized": true
        }
      }
    },
    "blocks": {
      "type": "dynamiczone",
      "components": [
        "blocks.banner",
        "blocks.button-group",
        "blocks.description",
        "blocks.gallery",
        "blocks.logo-group",
        "blocks.quote",
        "blocks.icon-boxes",
        "blocks.slideshow",
        "blocks.testimonials",
        "blocks.text-and-image"
      ],
      "pluginOptions": {
        "i18n": {
          "localized": true
        }
      }
    },
    "hide_title": {
      "pluginOptions": {
        "i18n": {
          "localized": true
        }
      },
      "type": "boolean"
    },
    "seo": {
      "type": "component",
      "repeatable": false,
      "pluginOptions": {
        "i18n": {
          "localized": true
        }
      },
      "component": "shared.seo"
    }
  }
}
